hashcommit/__init__.py
hashcommit/args.py
hashcommit/commit.py
hashcommit/git.py
hashcommit/logging.py
hashcommit/main.py
hashcommit/utils.py
hashcommit/version.py
hashcommit-0.2.0.dist-info/LICENSE
hashcommit-0.2.0.dist-info/METADATA
hashcommit-0.2.0.dist-info/WHEEL
hashcommit-0.2.0.dist-info/entry_points.txt
hashcommit-0.2.0.dist-info/top_level.txt
hashcommit-0.2.0.dist-info/RECORD
