Metadata-Version: 2.1
Name: hashcommit
Version: 0.2.0
Summary: A tool to generate a Git commit with a specific hash part.
Home-page: https://github.com/wozniakpl/hashcommit
Author: Bartosz Woźniak
Author-email: bwozniakdev@protonmail.com
Classifier: Programming Language :: Python :: 3
Classifier: License :: OSI Approved :: MIT License
Classifier: Operating System :: OS Independent
Requires-Python: >=3.6
License-File: LICENSE
